pykeyboard/__init__.py
pykeyboard/inline_keyboard.py
pykeyboard/inline_pagination_keyboard.py
pykeyboard/reply_keyboard.py
pykeyboard2-0.1.6.dist-info/LICENSE
pykeyboard2-0.1.6.dist-info/METADATA
pykeyboard2-0.1.6.dist-info/WHEEL
pykeyboard2-0.1.6.dist-info/top_level.txt
pykeyboard2-0.1.6.dist-info/RECORD
