Metadata-Version: 2.2
Name: pykeyboard2
Version: 0.1.6
Summary: Best Keyboard and Pagination for the Pyrogram Library.
Author: Vivek Kumar
License: MIT
Project-URL: Source, https://github.com/Vivekkumar-in/pykeyboard
Classifier: Programming Language :: Python :: 3.9
Classifier: Programming Language :: Python :: 3.10
Classifier: Programming Language :: Python :: 3.11
Classifier: Programming Language :: Python :: 3.12
Classifier: License :: OSI Approved :: MIT License
Requires-Python: >=3.9
License-File: LICENSE
